{"geonames":[{"lng":"0","geonameId":6295630,"name":"Earth","fclName":"parks,area, ...","toponymName":"Earth","fcodeName":"area","adminName1":"","lat":"0","fcl":"L","fcode":"AREA","population":6814400000},{"lng":"89.29688","geonameId":6255147,"name":"Asia","fclName":"parks,area, ...","toponymName":"Asia","fcodeName":"continent","adminName1":"","lat":"29.84064","fcl":"L","fcode":"CONT","population":3812366000},{"adminCode1":"00","lng":"34.75","geonameId":294640,"toponymName":"State of Israel","countryId":"294640","fcl":"A","population":7353985,"countryCode":"IL","name":"Israel","fclName":"country, state, region,...","countryName":"Israel","fcodeName":"independent political entity","adminName1":"","lat":"31.5","fcode":"PCLI"},{"adminCode1":"05","lng":"34.79995","geonameId":293396,"toponymName":"Tel Aviv District","countryId":"294640","fcl":"A","population":1221600,"countryCode":"IL","name":"Tel Aviv","fclName":"country, state, region,...","adminCodes1":{"ISO3166_2":"TA"},"countryName":"Israel","fcodeName":"first-order administrative division","adminName1":"Tel Aviv","lat":"32.08414","fcode":"ADM1"},{"adminCode1":"05","lng":"34.78057","geonameId":293397,"toponymName":"Tel Aviv","countryId":"294640","fcl":"P","population":432892,"countryCode":"IL","name":"Tel Aviv","fclName":"city, village,...","adminCodes1":{"ISO3166_2":"TA"},"countryName":"Israel","fcodeName":"seat of a first-order administrative division","adminName1":"Tel Aviv","lat":"32.08088","fcode":"PPLA"},{"adminCode1":"05","lng":"34.7689","geonameId":8598990,"toponymName":"Kerem HaTemanim","countryId":"294640","fcl":"P","population":0,"countryCode":"IL","name":"Kerem HaTemanim","fclName":"city, village,...","adminCodes1":{"ISO3166_2":"TA"},"countryName":"Israel","fcodeName":"section of populated place","adminName1":"Tel Aviv","lat":"32.06948","fcode":"PPLX"}]}